pycon25cvonew/__init__.py
pycon25cvonew/py.typed
pycon25cvonew/pycon25cvonew.py
pycon25cvonew-0.1.0.dist-info/WHEEL
pycon25cvonew-0.1.0.dist-info/METADATA
pycon25cvonew-0.1.0.dist-info/RECORD
