Metadata-Version: 2.3
Name: pycon25cvonew
Version: 0.1.0
Summary: Pycon Demo
Author: Carlo van Overbeek
Author-email: Carlo van Overbeek <cvanoverbeek@schubergphilis.com>
Classifier: License :: OSI Approved :: Apache Software License
Classifier: Programming Language :: Python :: 3.12
Requires-Python: >=3.12
